simple_mail_sender/__init__.py
simple_mail_sender/mail_sender.py
simple_mail_sender/setup.py
andriatina_mail_sender-0.0.9.dist-info/METADATA
andriatina_mail_sender-0.0.9.dist-info/WHEEL
andriatina_mail_sender-0.0.9.dist-info/top_level.txt
andriatina_mail_sender-0.0.9.dist-info/RECORD
